deadline/ae_adaptor/__init__.py
deadline/ae_adaptor/_version.py
deadline/ae_adaptor/AEAdaptor/AEAdaptor.json
deadline/ae_adaptor/AEAdaptor/__init__.py
deadline/ae_adaptor/AEAdaptor/__main__.py
deadline/ae_adaptor/AEAdaptor/adaptor.py
deadline/ae_adaptor/AEAdaptor/py.typed
deadline/ae_adaptor/AEAdaptor/schemas/init_data.schema.json
deadline/ae_adaptor/AEAdaptor/schemas/run_data.schema.json
deadline/ae_adaptor/AEClient/__init__.py
deadline/ae_adaptor/AEClient/ae_client.py
deadline/ae_adaptor/AEClient/ae_handler.py
deadline/ae_adaptor/AEClient/ipc.py
deadline/ae_submitter/DeadlineVersionRequirement.jsx
deadline/ae_submitter/Imports.jsx
deadline/ae_submitter/OpenAESubmitter.jsx
deadline/ae_submitter/UI/AESubmitterUI.jsx
deadline/ae_submitter/UI/CloseButton.jsx
deadline/ae_submitter/UI/SettingsWindow.jsx
deadline/ae_submitter/UI/SubmitButton.jsx
deadline/ae_submitter/UI/SubmitLayersWindow.jsx
deadline/ae_submitter/ae_templates/parameter_values.json
deadline/ae_submitter/ae_templates/template.json
deadline/ae_submitter/data/DeadlineData.jsx
deadline/ae_submitter/data/InitData.jsx
deadline/ae_submitter/data/Property.jsx
deadline/ae_submitter/polyfill/index.js
deadline/ae_submitter/submission/AssetReferenceTemplate.jsx
deadline/ae_submitter/submission/DataTemplate.jsx
deadline/ae_submitter/submission/JobTemplate.jsx
deadline/ae_submitter/submission/SubmitBundle.jsx
deadline/ae_submitter/utils/AeUtil.jsx
deadline/ae_submitter/utils/DeadlineCommands.jsx
deadline/ae_submitter/utils/Logger.jsx
deadline/ae_submitter/utils/Settings.jsx
deadline/ae_submitter/utils/Util.jsx
deadline_cloud_for_after_effects-0.1.2.dist-info/METADATA
deadline_cloud_for_after_effects-0.1.2.dist-info/WHEEL
deadline_cloud_for_after_effects-0.1.2.dist-info/entry_points.txt
deadline_cloud_for_after_effects-0.1.2.dist-info/licenses/LICENSE
deadline_cloud_for_after_effects-0.1.2.dist-info/licenses/NOTICE
deadline_cloud_for_after_effects-0.1.2.dist-info/RECORD
