Metadata-Version: 2.3
Name: deadline-cloud-for-after-effects
Version: 0.1.2
Summary: AWS Deadline Cloud for After Effects
Project-URL: Homepage, https://github.com/aws-deadline/deadline-cloud-for-after-effects
Project-URL: Source, https://github.com/aws-deadline/deadline-cloud-for-after-effects
Author: Amazon Web Services
License-Expression: Apache-2.0
License-File: LICENSE
License-File: NOTICE
Classifier: Development Status :: 3 - Alpha
Classifier: Intended Audience :: Developers
Classifier: Intended Audience :: End Users/Desktop
Classifier: License :: OSI Approved :: Apache Software License
Classifier: Operating System :: MacOS
Classifier: Operating System :: Microsoft :: Windows
Classifier: Programming Language :: Python
Classifier: Programming Language :: Python :: 3 :: Only
Classifier: Programming Language :: Python :: 3.9
Classifier: Programming Language :: Python :: 3.10
Classifier: Programming Language :: Python :: 3.11
Classifier: Programming Language :: Python :: 3.12
Requires-Python: >=3.9
Requires-Dist: deadline==0.48.*
Requires-Dist: openjd-adaptor-runtime==0.7.*
